qtciutil/__init__.py
qtciutil/qtciutil.py
qtciutil-0.0.6.dist-info/LICENSE
qtciutil-0.0.6.dist-info/METADATA
qtciutil-0.0.6.dist-info/WHEEL
qtciutil-0.0.6.dist-info/top_level.txt
qtciutil-0.0.6.dist-info/RECORD
