Metadata-Version: 2.1
Name: qtciutil
Version: 0.0.6
Summary: Some basic python methods for building CI for qt projects.
Home-page: https://github.com/l2m2/qt-ci-util
Author: l2m2
Author-email: l2m2lq@gmail.com
License: UNKNOWN
Platform: UNKNOWN
Classifier: Programming Language :: Python :: 3
Classifier: License :: OSI Approved :: MIT License
Classifier: Operating System :: OS Independent
Requires-Python: >=3.6
